veloweb/__init__.py
veloweb/app.py
veloweb/blueprints.py
veloweb/exceptions.py
veloweb/hasher.py
veloweb/jwt.py
veloweb/limiter.py
veloweb/mailer.py
veloweb/sanitizer.py
veloweb/session.py
veloweb/wtf.py
VeloWeb-2.0.1.dist-info/METADATA
VeloWeb-2.0.1.dist-info/WHEEL
VeloWeb-2.0.1.dist-info/entry_points.txt
VeloWeb-2.0.1.dist-info/top_level.txt
VeloWeb-2.0.1.dist-info/RECORD
